LEMApiClient/__init__.py
LEMApiClient/api_client.py
lem_api_client-0.6.dist-info/METADATA
lem_api_client-0.6.dist-info/WHEEL
lem_api_client-0.6.dist-info/entry_points.txt
lem_api_client-0.6.dist-info/top_level.txt
lem_api_client-0.6.dist-info/RECORD
