Metadata-Version: 2.1
Name: lem-api-client
Version: 0.6
Requires-Dist: requests
